[
  {
    "_id": "0742",
    "Number": "722",
    "Name": "Rowlet",
    "Element": "Grass",
    "SecElement": "Flying",
    "Height": "0.3 m",
    "Weight": "1.5 kg",
    "Species": "Grass Quill Pokémon",
    "Region": "Alola",
    "PkdxEntry": "This wary Pokémon uses photosynthesis to store up energy during the day, while becoming active at night.",
    "ImgUrl": "https://img.pokemondb.net/sprites/home/normal/rowlet.png",
    "Form": ""
  },
  {
    "_id": "0743",
    "Number": "723",
    "Name": "Dartrix",
    "Element": "Grass",
    "SecElement": "Flying",
    "Height": "0.7 m",
    "Weight": "16.0 kg",
    "Species": "Blade Quill Pokémon",
    "Region": "Alola",
    "PkdxEntry": "A bit of a dandy, it spends its free time preening its wings. Its preoccupation with any dirt on its plumage can leave it unable to battle.",
    "ImgUrl": "https://img.pokemondb.net/sprites/home/normal/dartrix.png",
    "Form": ""
  },
  {
    "_id": "0744",
    "Number": "724",
    "Name": "Decidueye",
    "Element": "Grass",
    "SecElement": "Ghost",
    "Height": "1.6 m",
    "Weight": "36.6 kg",
    "Species": "Arrow Quill Pokémon",
    "Region": "Alola",
    "PkdxEntry": "It fires arrow quills from its wings with such precision, they can pierce a pebble at distances over a hundred yards.",
    "ImgUrl": "https://img.pokemondb.net/sprites/home/normal/decidueye.png",
    "Form": ""
  },
  {
    "_id": "0745",
    "Number": "725",
    "Name": "Litten",
    "Element": "Fire",
    "SecElement": "",
    "Height": "0.4 m",
    "Weight": "4.3 kg",
    "Species": "Fire Cat Pokémon",
    "Region": "Alola",
    "PkdxEntry": "While grooming itself, it builds up fur inside its stomach. It sets the fur alight and spews fiery attacks, which change based on how it coughs.",
    "ImgUrl": "https://img.pokemondb.net/sprites/home/normal/litten.png",
    "Form": ""
  },
  {
    "_id": "0746",
    "Number": "726",
    "Name": "Torracat",
    "Element": "Fire",
    "SecElement": "",
    "Height": "0.7 m",
    "Weight": "25.0 kg",
    "Species": "Fire Cat Pokémon",
    "Region": "Alola",
    "PkdxEntry": "At its throat, it bears a bell of fire. The bell rings brightly whenever this Pokémon spits fire.",
    "ImgUrl": "https://img.pokemondb.net/sprites/home/normal/torracat.png",
    "Form": ""
  },
  {
    "_id": "0747",
    "Number": "727",
    "Name": "Incineroar",
    "Element": "Fire",
    "SecElement": "Dark",
    "Height": "1.8 m",
    "Weight": "83.0 kg",
    "Species": "Heel Pokémon",
    "Region": "Alola",
    "PkdxEntry": "This Pokémon has a violent, selfish disposition. If it’s not in the mood to listen, it will ignore its Trainer’s orders with complete nonchalance.",
    "ImgUrl": "https://img.pokemondb.net/sprites/home/normal/incineroar.png",
    "Form": ""
  },
  {
    "_id": "0748",
    "Number": "728",
    "Name": "Popplio",
    "Element": "Water",
    "SecElement": "",
    "Height": "0.4 m",
    "Weight": "7.5 kg",
    "Species": "Sea Lion Pokémon",
    "Region": "Alola",
    "PkdxEntry": "This Pokémon snorts body fluids from its nose, blowing balloons to smash into its foes. It’s famous for being a hard worker.",
    "ImgUrl": "https://img.pokemondb.net/sprites/home/normal/popplio.png",
    "Form": ""
  },
  {
    "_id": "0749",
    "Number": "729",
    "Name": "Brionne",
    "Element": "Water",
    "SecElement": "",
    "Height": "0.6 m",
    "Weight": "17.5 kg",
    "Species": "Pop Star Pokémon",
    "Region": "Alola",
    "PkdxEntry": "A skillful dancer, it creates a sequence of water balloons as it dances, and briskly bombards its enemies.",
    "ImgUrl": "https://img.pokemondb.net/sprites/home/normal/brionne.png",
    "Form": ""
  },
  {
    "_id": "0750",
    "Number": "730",
    "Name": "Primarina",
    "Element": "Water",
    "SecElement": "Fairy",
    "Height": "1.8 m",
    "Weight": "44.0 kg",
    "Species": "Soloist Pokémon",
    "Region": "Alola",
    "PkdxEntry": "It controls its water balloons with song. The melody is learned from others of its kind and is passed down from one generation to the next.",
    "ImgUrl": "https://img.pokemondb.net/sprites/home/normal/primarina.png",
    "Form": ""
  },
  {
    "_id": "0751",
    "Number": "731",
    "Name": "Pikipek",
    "Element": "Normal",
    "SecElement": "Flying",
    "Height": "0.3 m",
    "Weight": "1.2 kg",
    "Species": "Woodpecker Pokémon",
    "Region": "Alola",
    "PkdxEntry": "It can peck at a rate of 16 times a second to drill holes in trees. It uses the holes for food storage and for nesting.",
    "ImgUrl": "https://img.pokemondb.net/sprites/home/normal/pikipek.png",
    "Form": ""
  },
  {
    "_id": "0752",
    "Number": "732",
    "Name": "Trumbeak",
    "Element": "Normal",
    "SecElement": "Flying",
    "Height": "0.6 m",
    "Weight": "14.8 kg",
    "Species": "Bugle Beak Pokémon",
    "Region": "Alola",
    "PkdxEntry": "It eats berries and stores their seeds in its beak. When it encounters enemies or prey, it fires off all the seeds in a burst.",
    "ImgUrl": "https://img.pokemondb.net/sprites/home/normal/trumbeak.png",
    "Form": ""
  },
  {
    "_id": "0753",
    "Number": "733",
    "Name": "Toucannon",
    "Element": "Normal",
    "SecElement": "Flying",
    "Height": "1.1 m",
    "Weight": "26.0 kg",
    "Species": "Cannon Pokémon",
    "Region": "Alola",
    "PkdxEntry": "When it battles, its beak heats up. The temperature can easily exceed 212 degrees Fahrenheit, causing severe burns when it hits.",
    "ImgUrl": "https://img.pokemondb.net/sprites/home/normal/toucannon.png",
    "Form": ""
  },
  {
    "_id": "0754",
    "Number": "734",
    "Name": "Yungoos",
    "Element": "Normal",
    "SecElement": "",
    "Height": "0.4 m",
    "Weight": "6.0 kg",
    "Species": "Loitering Pokémon",
    "Region": "Alola",
    "PkdxEntry": "\tWith its sharp fangs, it will bite anything. It did not originally live in Alola but was imported from another region.",
    "ImgUrl": "https://img.pokemondb.net/sprites/home/normal/yungoos.png",
    "Form": ""
  },
  {
    "_id": "0755",
    "Number": "735",
    "Name": "Gumshoos",
    "Element": "Normal",
    "SecElement": "",
    "Height": "0.7 m",
    "Weight": "14.2 kg",
    "Species": "Stakeout Pokémon",
    "Region": "Alola",
    "PkdxEntry": "When it finds a trace of its prey, it patiently stakes out the location...but it’s always snoozing by nightfall.",
    "ImgUrl": "https://img.pokemondb.net/sprites/home/normal/gumshoos.png",
    "Form": ""
  },
  {
    "_id": "0756",
    "Number": "736",
    "Name": "Grubbin",
    "Element": "Bug",
    "SecElement": "",
    "Height": "0.4 m",
    "Weight": "4.4 kg",
    "Species": "Larva Pokémon",
    "Region": "Alola",
    "PkdxEntry": "Its strong jaw enables it to scrape trees and slurp out the sap. It normally lives underground.",
    "ImgUrl": "https://img.pokemondb.net/sprites/home/normal/grubbin.png",
    "Form": ""
  },
  {
    "_id": "0757",
    "Number": "737",
    "Name": "Charjabug",
    "Element": "Bug",
    "SecElement": "Electric",
    "Height": "0.5 m",
    "Weight": "10.5 kg",
    "Species": "Battery Pokémon",
    "Region": "Alola",
    "PkdxEntry": "Its body is capable of storing electricity. On camping trips, people are grateful to have one around.",
    "ImgUrl": "https://img.pokemondb.net/sprites/home/normal/charjabug.png",
    "Form": ""
  },
  {
    "_id": "0758",
    "Number": "738",
    "Name": "Vikavolt",
    "Element": "Bug",
    "SecElement": "Electric",
    "Height": "1.5 m",
    "Weight": "45.0 kg",
    "Species": "Stag Beetle Pokémon",
    "Region": "Alola",
    "PkdxEntry": "It zips around, on sharp lookout for an opening. It concentrates electrical energy within its large jaws and uses it to zap its enemies.",
    "ImgUrl": "https://img.pokemondb.net/sprites/home/normal/vikavolt.png",
    "Form": ""
  },
  {
    "_id": "0759",
    "Number": "739",
    "Name": "Crabrawler",
    "Element": "Fighting",
    "SecElement": "",
    "Height": "0.6 m",
    "Weight": "7.0 kg",
    "Species": "Boxing Pokémon",
    "Region": "Alola",
    "PkdxEntry": "While guarding its weak points with its pincers, it looks for an opening and unleashes punches. When it loses, it foams at the mouth and faints.",
    "ImgUrl": "https://img.pokemondb.net/sprites/home/normal/crabrawler.png",
    "Form": ""
  },
  {
    "_id": "0760",
    "Number": "740",
    "Name": "Crabominable",
    "Element": "Fighting",
    "SecElement": "Ice",
    "Height": "1.7 m",
    "Weight": "180.0 kg",
    "Species": "Woolly Crab Pokémon",
    "Region": "Alola",
    "PkdxEntry": "It aimed for the top but got lost and ended up on a snowy mountain. Being forced to endure the cold, this Pokémon evolved and grew fur.",
    "ImgUrl": "https://img.pokemondb.net/sprites/home/normal/crabominable.png",
    "Form": ""
  },
  {
    "_id": "0761",
    "Number": "741",
    "Name": "Oricorio",
    "Element": "Fire",
    "SecElement": "Flying",
    "Height": "0.6 m",
    "Weight": "3.4 kg",
    "Species": "Dancing Pokémon",
    "Region": "Alola",
    "PkdxEntry": "It beats its wings together to create fire. As it moves in the steps of its beautiful dance, it bathes opponents in intense flames.",
    "ImgUrl": "https://img.pokemondb.net/sprites/home/normal/oricorio-baile.png",
    "Form": "Baile Style"
  },
  {
    "_id": "0762",
    "Number": "741",
    "Name": "Oricorio",
    "Element": "Psychic",
    "SecElement": "Flying",
    "Height": "0.6 m",
    "Weight": "3.4 kg",
    "Species": "Dancing Pokémon",
    "Region": "Alola",
    "PkdxEntry": "It relaxes its opponents with its elegant dancing. When they let their guard down, it showers them with psychic energy.",
    "ImgUrl": "https://img.pokemondb.net/sprites/home/normal/oricorio-pau.png",
    "Form": "Pa'u Style"
  },
  {
    "_id": "0763",
    "Number": "741",
    "Name": "Oricorio",
    "Element": "Electric",
    "SecElement": "Flying",
    "Height": "0.6 m",
    "Weight": "3.4 kg",
    "Species": "Dancing Pokémon",
    "Region": "Alola",
    "PkdxEntry": "It creates an electric charge by rubbing its feathers together. It dances over to its enemies and delivers shocking electrical punches.",
    "ImgUrl": "https://img.pokemondb.net/sprites/home/normal/oricorio-pom-pom.png",
    "Form": "Pom Pom Style"
  },
  {
    "_id": "0764",
    "Number": "741",
    "Name": "Oricorio",
    "Element": "Ghost",
    "SecElement": "Flying",
    "Height": "0.6 m",
    "Weight": "3.4 kg",
    "Species": "Dancing Pokémon",
    "Region": "Alola",
    "PkdxEntry": "It summons the dead with its dreamy dancing. From their malice, it draws power with which to curse its enemies.",
    "ImgUrl": "https://img.pokemondb.net/sprites/home/normal/oricorio-sensu.png",
    "Form": "Sensu Style"
  },
  {
    "_id": "0765",
    "Number": "742",
    "Name": "Cutiefly",
    "Element": "Bug",
    "SecElement": "Fairy",
    "Height": "0.1 m",
    "Weight": "0.2 kg",
    "Species": "Bee Fly Pokémon",
    "Region": "Alola",
    "PkdxEntry": "It feeds on the nectar and pollen of flowers. Because it’s able to sense auras, it can identify which flowers are about to bloom.",
    "ImgUrl": "https://img.pokemondb.net/sprites/home/normal/cutiefly.png",
    "Form": ""
  },
  {
    "_id": "0766",
    "Number": "743",
    "Name": "Ribombee",
    "Element": "Bug",
    "SecElement": "Fairy",
    "Height": "0.2 m",
    "Weight": "0.5 kg",
    "Species": "Bee Fly Pokémon",
    "Region": "Alola",
    "PkdxEntry": "It rolls up pollen into puffs. It makes many different varieties, some used as food and others used in battle.",
    "ImgUrl": "https://img.pokemondb.net/sprites/home/normal/ribombee.png",
    "Form": ""
  },
  {
    "_id": "0767",
    "Number": "744",
    "Name": "Rockruff",
    "Element": "Rock",
    "SecElement": "",
    "Height": "0.5 m",
    "Weight": "9.2 kg",
    "Species": "Puppy Pokémon",
    "Region": "Alola",
    "PkdxEntry": "It’s considered to be a good Pokémon for beginners because of its friendliness, but its disposition grows rougher as it grows up.",
    "ImgUrl": "https://img.pokemondb.net/sprites/home/normal/rockruff.png",
    "Form": ""
  },
  {
    "_id": "0768",
    "Number": "745",
    "Name": "Lycanroc",
    "Element": "Rock",
    "SecElement": "",
    "Height": "0.8 m",
    "Weight": "25.0 kg",
    "Species": "Wolf Pokémon",
    "Region": "Alola",
    "PkdxEntry": "Its quick movements confuse its enemies. Well equipped with claws and fangs, it also uses the sharp rocks in its mane as weapons.",
    "ImgUrl": "https://img.pokemondb.net/sprites/home/normal/lycanroc-midday.png",
    "Form": "Midday Form"
  },
  {
    "_id": "0769",
    "Number": "745",
    "Name": "Lycanroc",
    "Element": "Rock",
    "SecElement": "",
    "Height": "1.1 m",
    "Weight": "25.0 kg",
    "Species": "Wolf Pokémon",
    "Region": "Alola",
    "PkdxEntry": "The more intimidating the opponent it faces, the more this Pokémon’s blood boils. It will attack with no regard for its own safety.",
    "ImgUrl": "https://img.pokemondb.net/sprites/home/normal/lycanroc-midnight.png",
    "Form": "Midnight Form"
  },
  {
    "_id": "0770",
    "Number": "745",
    "Name": "Lycanroc",
    "Element": "Rock",
    "SecElement": "",
    "Height": "0.8 m",
    "Weight": "25.0 kg",
    "Species": "Wolf Pokémon",
    "Region": "Alola",
    "PkdxEntry": "This strange form is the result of its evolving at dusk. It’s very rare in Alola.",
    "ImgUrl": "https://img.pokemondb.net/sprites/home/normal/lycanroc-dusk.png",
    "Form": "Dusk Form"
  },
  {
    "_id": "0771",
    "Number": "746",
    "Name": "Wishiwashi",
    "Element": "Water",
    "SecElement": "",
    "Height": "0.2 m",
    "Weight": "0.3 kg",
    "Species": "Small Fry Pokémon",
    "Region": "Alola",
    "PkdxEntry": "SWhen it’s in trouble, its eyes moisten and begin to shine. The shining light attracts its comrades, and they stand together against their enemies.",
    "ImgUrl": "https://img.pokemondb.net/sprites/home/normal/wishiwashi.png",
    "Form": ""
  },
  {
    "_id": "0772",
    "Number": "747",
    "Name": "Mareanie",
    "Element": "Poison",
    "SecElement": "Water",
    "Height": "0.4 m",
    "Weight": "8.0 kg",
    "Species": "Brutal Star Pokémon",
    "Region": "Alola",
    "PkdxEntry": "It’s found crawling on beaches and seafloors. The coral that grows on Corsola’s head is as good as a five-star banquet to this Pokémon.",
    "ImgUrl": "https://img.pokemondb.net/sprites/home/normal/mareanie.png",
    "Form": ""
  },
  {
    "_id": "0773",
    "Number": "748",
    "Name": "Toxapex",
    "Element": "Poison",
    "SecElement": "Water",
    "Height": "0.7 m",
    "Weight": "14.5 kg",
    "Species": "Brutal Star Pokémon",
    "Region": "Alola",
    "PkdxEntry": "To attack, this Pokémon sends toxic spikes flying at its enemies. Ones that come close get mown down by the claws on its feet.",
    "ImgUrl": "https://img.pokemondb.net/sprites/home/normal/toxapex.png",
    "Form": ""
  },
  {
    "_id": "0774",
    "Number": "749",
    "Name": "Mudbray",
    "Element": "Ground",
    "SecElement": "",
    "Height": "1.0 m",
    "Weight": "110.0 kg",
    "Species": "Donkey Pokémon",
    "Region": "Alola",
    "PkdxEntry": "It has a stubborn, individualistic disposition. Eating dirt, making mud, and playing in the mire all form part of its daily routine.",
    "ImgUrl": "https://img.pokemondb.net/sprites/home/normal/mudbray.png",
    "Form": ""
  },
  {
    "_id": "0775",
    "Number": "750",
    "Name": "Mudsdale",
    "Element": "Ground",
    "SecElement": "",
    "Height": "2.5 m",
    "Weight": "920.0 kg",
    "Species": "Draft Horse Pokémon",
    "Region": "Alola",
    "PkdxEntry": "It spits a mud that provides resistance to both wind and rain, so the walls of old houses were often coated with it.",
    "ImgUrl": "https://img.pokemondb.net/sprites/home/normal/mudsdale.png",
    "Form": ""
  },
  {
    "_id": "0776",
    "Number": "751",
    "Name": "Dewpider",
    "Element": "Water",
    "SecElement": "Bug",
    "Height": "0.3 m",
    "Weight": "4.0 kg",
    "Species": "Water Bubble Pokémon",
    "Region": "Alola",
    "PkdxEntry": "It crawls onto the land in search of food. Its water bubble allows it to breathe and protects its soft head.",
    "ImgUrl": "https://img.pokemondb.net/sprites/home/normal/dewpider.png",
    "Form": ""
  },
  {
    "_id": "0777",
    "Number": "752",
    "Name": "Araquanid",
    "Element": "Water",
    "SecElement": "Bug",
    "Height": "1.8 m",
    "Weight": "82.0 kg",
    "Species": "Water Bubble Pokémon",
    "Region": "Alola",
    "PkdxEntry": "It delivers headbutts with the water bubble on its head. Small Pokémon get sucked into the bubble, where they drown.",
    "ImgUrl": "https://img.pokemondb.net/sprites/home/normal/araquanid.png",
    "Form": ""
  },
  {
    "_id": "0778",
    "Number": "753",
    "Name": "Fomantis",
    "Element": "Grass",
    "SecElement": "",
    "Height": "0.3 m",
    "Weight": "1.5 kg",
    "Species": "Sickle Grass Pokémon",
    "Region": "Alola",
    "PkdxEntry": "During the day, it sleeps and soaks up light. When night falls, it walks around looking for a safer place to sleep.",
    "ImgUrl": "https://img.pokemondb.net/sprites/home/normal/fomantis.png",
    "Form": ""
  },
  {
    "_id": "0779",
    "Number": "754",
    "Name": "Lurantis",
    "Element": "Grass",
    "SecElement": "",
    "Height": "0.9 m",
    "Weight": "18.5 kg",
    "Species": "Bloom Sickle Pokémon",
    "Region": "Alola",
    "PkdxEntry": "It fires beams from its sickle-shaped petals. These beams are powerful enough to cleave through thick metal plates.",
    "ImgUrl": "https://img.pokemondb.net/sprites/home/normal/lurantis.png",
    "Form": ""
  },
  {
    "_id": "0780",
    "Number": "755",
    "Name": "Morelull",
    "Element": "Grass",
    "SecElement": "Fairy",
    "Height": "0.2 m",
    "Weight": "1.5 kg",
    "Species": "Illuminating Pokémon",
    "Region": "Alola",
    "PkdxEntry": "It scatters spores that flicker and glow. Anyone seeing these lights falls into a deep slumber.",
    "ImgUrl": "https://img.pokemondb.net/sprites/home/normal/morelull.png",
    "Form": ""
  },
  {
    "_id": "0781",
    "Number": "756",
    "Name": "Shiinotic",
    "Element": "Grass",
    "SecElement": "Fairy",
    "Height": "1.0 m",
    "Weight": "11.5 kg",
    "Species": "Illuminating Pokémon",
    "Region": "Alola",
    "PkdxEntry": "It emits flickering spores that cause drowsiness. When its prey succumb to sleep, this Pokémon feeds on them by sucking in their energy.",
    "ImgUrl": "https://img.pokemondb.net/sprites/home/normal/shiinotic.png",
    "Form": ""
  },
  {
    "_id": "0782",
    "Number": "757",
    "Name": "Salandit",
    "Element": "Poison",
    "SecElement": "Fire",
    "Height": "0.6 m",
    "Weight": "4.8 kg",
    "Species": "Toxic Lizard Pokémon",
    "Region": "Alola",
    "PkdxEntry": "It burns its bodily fluids to create a poisonous gas. When its enemies become disoriented from inhaling the gas, it attacks them.",
    "ImgUrl": "https://img.pokemondb.net/sprites/home/normal/salandit.png",
    "Form": ""
  },
  {
    "_id": "0783",
    "Number": "758",
    "Name": "Salazzle",
    "Element": "Poison",
    "SecElement": "Fire",
    "Height": "1.2 m",
    "Weight": "22.2 kg",
    "Species": "Toxic Lizard Pokémon",
    "Region": "Alola",
    "PkdxEntry": "Filled with pheromones, its poisonous gas can be diluted to use in the production of luscious perfumes.",
    "ImgUrl": "https://img.pokemondb.net/sprites/home/normal/salazzle.png",
    "Form": ""
  },
  {
    "_id": "0784",
    "Number": "759",
    "Name": "Stufful",
    "Element": "Normal",
    "SecElement": "Fighting",
    "Height": "0.5 m",
    "Weight": "6.8 kg",
    "Species": "Flailing Pokémon",
    "Region": "Alola",
    "PkdxEntry": "Despite its adorable appearance, when it gets angry and flails about, its arms and legs could knock a pro wrestler sprawling.",
    "ImgUrl": "https://img.pokemondb.net/sprites/home/normal/stufful.png",
    "Form": ""
  },
  {
    "_id": "0785",
    "Number": "760",
    "Name": "Bewear",
    "Element": "Normal",
    "SecElement": "Fighting",
    "Height": "2.1 m",
    "Weight": "135.0 kg",
    "Species": "Strong Arm Pokémon",
    "Region": "Alola",
    "PkdxEntry": "This immensely dangerous Pokémon possesses overwhelming physical strength. Its habitat is generally off-limits.",
    "ImgUrl": "https://img.pokemondb.net/sprites/home/normal/bewear.png",
    "Form": ""
  },
  {
    "_id": "0786",
    "Number": "761",
    "Name": "Bounsweet",
    "Element": "Grass",
    "SecElement": "",
    "Height": "0.3 m",
    "Weight": "3.2 kg",
    "Species": "Fruit Pokémon",
    "Region": "Alola",
    "PkdxEntry": "A delectable aroma pours from its body. They are often swallowed whole by Toucannon lured by that wafting deliciousness.",
    "ImgUrl": "https://img.pokemondb.net/sprites/home/normal/bounsweet.png",
    "Form": ""
  },
  {
    "_id": "0787",
    "Number": "762",
    "Name": "Steenee",
    "Element": "Grass",
    "SecElement": "",
    "Height": "0.7 m",
    "Weight": "8.2 kg",
    "Species": "Fruit Pokémon",
    "Region": "Alola",
    "PkdxEntry": "The sepals on its head developed to protect its body. These are quite hard, so even if pecked by bird Pokémon, this Pokémon is totally fine.",
    "ImgUrl": "https://img.pokemondb.net/sprites/home/normal/steenee.png",
    "Form": ""
  },
  {
    "_id": "0788",
    "Number": "763",
    "Name": "Tsareena",
    "Element": "Grass",
    "SecElement": "",
    "Height": "1.2 m",
    "Weight": "21.4 kg",
    "Species": "Fruit Pokémon",
    "Region": "Alola",
    "PkdxEntry": "A Pokémon known for the beauty of its well-shaped legs, it sometimes appears as a mascot in advertisements for beauty salons.",
    "ImgUrl": "https://img.pokemondb.net/sprites/home/normal/tsareena.png",
    "Form": ""
  },
  {
    "_id": "0789",
    "Number": "764",
    "Name": "Comfey",
    "Element": "Fairy",
    "SecElement": "",
    "Height": "0.1 m",
    "Weight": "0.3 kg",
    "Species": "Posy Picker Pokémon",
    "Region": "Alola",
    "PkdxEntry": "It attaches flowers to its highly nutritious vine. This revitalizes the flowers, and they give off an aromatic scent.",
    "ImgUrl": "https://img.pokemondb.net/sprites/home/normal/comfey.png",
    "Form": ""
  },
  {
    "_id": "0790",
    "Number": "765",
    "Name": "Oranguru",
    "Element": "Normal",
    "SecElement": "Psychic",
    "Height": "1.5 m",
    "Weight": "76.0 kg",
    "Species": "Sage Pokémon",
    "Region": "Alola",
    "PkdxEntry": "Known for its extreme intelligence, this Pokémon will look down on inexperienced Trainers, so it’s best suited to veteran Trainers.",
    "ImgUrl": "https://img.pokemondb.net/sprites/home/normal/oranguru.png",
    "Form": ""
  },
  {
    "_id": "0791",
    "Number": "766",
    "Name": "Passimian",
    "Element": "Fighting",
    "SecElement": "",
    "Height": "2.0 m",
    "Weight": "82.8 kg",
    "Species": "Teamwork Pokémon",
    "Region": "Alola",
    "PkdxEntry": "They form groups of roughly 20 individuals. Their mutual bond is remarkable—they will never let down a comrade.",
    "ImgUrl": "https://img.pokemondb.net/sprites/home/normal/passimian.png",
    "Form": ""
  },
  {
    "_id": "0792",
    "Number": "767",
    "Name": "Wimpod",
    "Element": "Bug",
    "SecElement": "Water",
    "Height": "0.5 m",
    "Weight": "12.0 kg",
    "Species": "Turn Tail Pokémon",
    "Region": "Alola",
    "PkdxEntry": "This Pokémon is a coward. As it desperately dashes off, the flailing of its many legs leaves a sparkling clean path in its wake.",
    "ImgUrl": "https://img.pokemondb.net/sprites/home/normal/wimpod.png",
    "Form": ""
  },
  {
    "_id": "0793",
    "Number": "768",
    "Name": "Golisopod",
    "Element": "Bug",
    "SecElement": "Water",
    "Height": "2.0 m",
    "Weight": "108.0 kg",
    "Species": "Hard Scale Pokémon",
    "Region": "Alola",
    "PkdxEntry": "With a flashing slash of its giant sharp claws, it cleaves seawater—or even air—right in two.",
    "ImgUrl": "https://img.pokemondb.net/sprites/home/normal/golisopod.png",
    "Form": ""
  },
  {
    "_id": "0794",
    "Number": "769",
    "Name": "Sandygast",
    "Element": "Ghost",
    "SecElement": "Ground",
    "Height": "0.5 m",
    "Weight": "70.0 kg",
    "Species": "Sand Heap Pokémon",
    "Region": "Alola",
    "PkdxEntry": "Born from a sand mound playfully built by a child, this Pokémon embodies the grudges of the departed.",
    "ImgUrl": "https://img.pokemondb.net/sprites/home/normal/sandygast.png",
    "Form": ""
  },
  {
    "_id": "0795",
    "Number": "770",
    "Name": "Palossand",
    "Element": "Ghost",
    "SecElement": "Ground",
    "Height": "1.3 m",
    "Weight": "250.0 kg",
    "Species": "Sand Castle Pokémon",
    "Region": "Alola",
    "PkdxEntry": "Possessed people controlled by this Pokémon transformed its sand mound into a castle. As it evolved, its power to curse grew ever stronger.",
    "ImgUrl": "https://img.pokemondb.net/sprites/home/normal/palossand.png",
    "Form": ""
  },
  {
    "_id": "0796",
    "Number": "771",
    "Name": "Pyukumuku",
    "Element": "Water",
    "SecElement": "",
    "Height": "0.3 m",
    "Weight": "1.2 kg",
    "Species": "Sea Cucumber Pokémon",
    "Region": "Alola",
    "PkdxEntry": "It lives in shallow seas, such as areas near a beach. It can eject its internal organs, which it uses to engulf its prey or battle enemies.",
    "ImgUrl": "https://img.pokemondb.net/sprites/home/normal/pyukumuku.png",
    "Form": ""
  },
  {
    "_id": "0797",
    "Number": "772",
    "Name": "Type: Null",
    "Element": "Normal",
    "SecElement": "",
    "Height": "1.9 m",
    "Weight": "120.5 kg",
    "Species": "Synthetic Pokémon",
    "Region": "Alola",
    "PkdxEntry": "The heavy control mask it wears suppresses its intrinsic capabilities. This Pokémon has some hidden special power.",
    "ImgUrl": "https://img.pokemondb.net/sprites/home/normal/type-null.png",
    "Form": ""
  },
  {
    "_id": "0798",
    "Number": "773",
    "Name": "Silvally",
    "Element": "Normal",
    "SecElement": "",
    "Height": "2.3 m",
    "Weight": "100.5 kg",
    "Species": "Synthetic Pokémon",
    "Region": "Alola",
    "PkdxEntry": "Its trust in its partner is what awakens it. This Pokémon is capable of changing its type, a flexibility that is well displayed in battle.",
    "ImgUrl": "https://img.pokemondb.net/sprites/home/normal/silvally.png",
    "Form": ""
  },
  {
    "_id": "0799",
    "Number": "774",
    "Name": "Minior",
    "Element": "Rock",
    "SecElement": "Flying",
    "Height": "0.3 m",
    "Weight": "40.0 kg",
    "Species": "Meteor Pokémon",
    "Region": "Alola",
    "PkdxEntry": "Originally making its home in the ozone layer, it hurtles to the ground when the shell enclosing its body grows too heavy.",
    "ImgUrl": "https://img.pokemondb.net/sprites/home/normal/minior.png",
    "Form": "https://img.pokemondb.net/sprites/home/normal/minior-red-core.png"
  },
  {
    "_id": "0800",
    "Number": "775",
    "Name": "Komala",
    "Element": "Normal",
    "SecElement": "",
    "Height": "0.4 m",
    "Weight": "19.9 kg",
    "Species": "Drowsing Pokémon",
    "Region": "Alola",
    "PkdxEntry": "It is born asleep, and it dies asleep. All its movements are apparently no more than the results of it tossing and turning in its dreams.",
    "ImgUrl": "https://img.pokemondb.net/sprites/home/normal/komala.png",
    "Form": ""
  },
  {
    "_id": "0801",
    "Number": "776",
    "Name": "Turtonator",
    "Element": "Fire",
    "SecElement": "Dragon",
    "Height": "2.0 m",
    "Weight": "212.0 kg",
    "Species": "Blast Turtle Pokémon",
    "Region": "Alola",
    "PkdxEntry": "The shell on its back is chemically unstable and explodes violently if struck. The hole in its stomach is its weak point.",
    "ImgUrl": "https://img.pokemondb.net/sprites/home/normal/turtonator.png",
    "Form": ""
  },
  {
    "_id": "0802",
    "Number": "777",
    "Name": "Togedemaru",
    "Element": "Electric",
    "SecElement": "Steel",
    "Height": "0.3 m",
    "Weight": "3.3 kg",
    "Species": "Roly-Poly Pokémon",
    "Region": "Alola",
    "PkdxEntry": "The spiny fur on its back is normally at rest. When this Pokémon becomes agitated, its fur stands on end and stabs into its attackers.",
    "ImgUrl": "https://img.pokemondb.net/sprites/home/normal/togedemaru.png",
    "Form": ""
  },
  {
    "_id": "0803",
    "Number": "778",
    "Name": "Mimikyu",
    "Element": "Ghost",
    "SecElement": "Fairy",
    "Height": "0.2 m",
    "Weight": "0.7 kg",
    "Species": "Disguise Pokémon",
    "Region": "Alola",
    "PkdxEntry": "After going to all the effort of disguising itself, its neck was broken. Whatever is inside is probably unharmed, but it’s still feeling sad.",
    "ImgUrl": "https://img.pokemondb.net/sprites/home/normal/mimikyu.png",
    "Form": ""
  },
  {
    "_id": "0804",
    "Number": "779",
    "Name": "Bruxish",
    "Element": "Water",
    "SecElement": "Psychic",
    "Height": "0.9 m",
    "Weight": "19.0 kg",
    "Species": "Gnash Teeth Pokémon",
    "Region": "Alola",
    "PkdxEntry": "When it unleashes its psychic power from the protuberance on its head, the grating sound of grinding teeth echoes through the area.",
    "ImgUrl": "https://img.pokemondb.net/sprites/home/normal/bruxish.png",
    "Form": ""
  },
  {
    "_id": "0805",
    "Number": "780",
    "Name": "Drampa",
    "Element": "Normal",
    "SecElement": "Dragon",
    "Height": "3.0 m",
    "Weight": "185.0 kg",
    "Species": "Placid Pokémon",
    "Region": "Alola",
    "PkdxEntry": "It has a compassionate personality, but if it is angered, it completely destroys its surroundings with its intense breath.",
    "ImgUrl": "https://img.pokemondb.net/sprites/home/normal/drampa.png",
    "Form": ""
  },
  {
    "_id": "0806",
    "Number": "781",
    "Name": "Dhelmise",
    "Element": "Ghost",
    "SecElement": "Grass",
    "Height": "3.9 m",
    "Weight": "210.0 kg",
    "Species": "Sea Creeper Pokémon",
    "Region": "Alola",
    "PkdxEntry": "Swinging its massive anchor, it can KO Wailord in a single blow. What appears to be green seaweed is actually its body.",
    "ImgUrl": "https://img.pokemondb.net/sprites/home/normal/dhelmise.png",
    "Form": ""
  },
  {
    "_id": "0807",
    "Number": "782",
    "Name": "Jangmo-o",
    "Element": "Dragon",
    "SecElement": "",
    "Height": "0.6 m",
    "Weight": "29.7 kg",
    "Species": "Scaly Pokémon",
    "Region": "Alola",
    "PkdxEntry": "It smacks the scales on its head against rocks or against the ground to frighten its opponents. It can also contact its friends with these noises.",
    "ImgUrl": "https://img.pokemondb.net/sprites/home/normal/jangmo-o.png",
    "Form": ""
  },
  {
    "_id": "0808",
    "Number": "783",
    "Name": "Hakamo-o",
    "Element": "Dragon",
    "SecElement": "Fighting",
    "Height": "1.3 m",
    "Weight": "47.0 kg",
    "Species": "Scaly Pokémon",
    "Region": "Alola",
    "PkdxEntry": "It leaps at its prey with a courageous shout. Its scaly punches tear its opponents to shreds.",
    "ImgUrl": "https://img.pokemondb.net/sprites/home/normal/hakamo-o.png",
    "Form": ""
  },
  {
    "_id": "0809",
    "Number": "784",
    "Name": "Kommo-o",
    "Element": "Dragon",
    "SecElement": "Fighting",
    "Height": "1.6 m",
    "Weight": "78.2 kg",
    "Species": "Scaly Pokémon",
    "Region": "Alola",
    "PkdxEntry": "When it spots enemies, it threatens them by jingling the scales on its tail. Weak opponents will crack and flee in panic.",
    "ImgUrl": "https://img.pokemondb.net/sprites/home/normal/kommo-o.png",
    "Form": ""
  },
  {
    "_id": "0810",
    "Number": "785",
    "Name": "Tapu Koko",
    "Element": "Electric",
    "SecElement": "Fairy",
    "Height": "1.8 m",
    "Weight": "20.5 kg",
    "Species": "Land Spirit Pokémon",
    "Region": "Alola",
    "PkdxEntry": "This guardian deity of Melemele is brimming with curiosity. It summons thunderclouds and stores their lightning inside its body.",
    "ImgUrl": "https://img.pokemondb.net/sprites/home/normal/tapu-koko.png",
    "Form": ""
  },
  {
    "_id": "0811",
    "Number": "786",
    "Name": "Tapu Lele",
    "Element": "Psychic",
    "SecElement": "Fairy",
    "Height": "1.2 m",
    "Weight": "18.6 kg",
    "Species": "Land Spirit Pokémon",
    "Region": "Alola",
    "PkdxEntry": "This guardian deity of Akala is guilelessly cruel. The fragrant aroma of flowers is the source of its energy.",
    "ImgUrl": "https://img.pokemondb.net/sprites/home/normal/tapu-lele.png",
    "Form": ""
  },
  {
    "_id": "0812",
    "Number": "787",
    "Name": "Tapu Bulu",
    "Element": "Grass",
    "SecElement": "Fairy",
    "Height": "1.9 m",
    "Weight": "45.5 kg",
    "Species": "Land Spirit Pokémon",
    "Region": "Alola",
    "PkdxEntry": "It pulls large trees up by the roots and swings them around. It causes vegetation to grow, and then it absorbs energy from the growth.",
    "ImgUrl": "https://img.pokemondb.net/sprites/home/normal/tapu-bulu.png",
    "Form": ""
  },
  {
    "_id": "0813",
    "Number": "788",
    "Name": "Tapu Fini",
    "Element": "Water",
    "SecElement": "Fairy",
    "Height": "1.3 m",
    "Weight": "21.2 kg",
    "Species": "Land Spirit Pokémon",
    "Region": "Alola",
    "PkdxEntry": "The dense fog it creates brings the downfall and destruction of its confused enemies. Ocean currents are the source of its energy.",
    "ImgUrl": "https://img.pokemondb.net/sprites/home/normal/tapu-fini.png",
    "Form": ""
  },
  {
    "_id": "0814",
    "Number": "789",
    "Name": "Cosmog",
    "Element": "Psychic",
    "SecElement": "",
    "Height": "0.2 m",
    "Weight": "0.1 kg",
    "Species": "Nebula Pokémon",
    "Region": "Alola",
    "PkdxEntry": "Its body is gaseous and frail. It slowly grows as it collects dust from the atmosphere.",
    "ImgUrl": "https://img.pokemondb.net/sprites/home/normal/cosmog.png",
    "Form": ""
  },
  {
    "_id": "0815",
    "Number": "790",
    "Name": "Cosmoem",
    "Element": "Psychic",
    "SecElement": "",
    "Height": "0.1 m",
    "Weight": "999.9 kg",
    "Species": "Protostar Pokémon",
    "Region": "Alola",
    "PkdxEntry": "Motionless as if dead, its body is faintly warm to the touch. In the distant past, it was called the cocoon of the stars.",
    "ImgUrl": "https://img.pokemondb.net/sprites/home/normal/cosmoem.png",
    "Form": ""
  },
  {
    "_id": "0816",
    "Number": "791",
    "Name": "Solgaleo",
    "Element": "Psychic",
    "SecElement": "Steel",
    "Height": "3.4 m",
    "Weight": "230.0 kg",
    "Species": "Sunne Pokémon",
    "Region": "Alola",
    "PkdxEntry": "This Pokémon is said to be a male evolution of Cosmog. At the activation of its third eye, it departs for another world.",
    "ImgUrl": "https://img.pokemondb.net/sprites/home/normal/solgaleo.png",
    "Form": ""
  },
  {
    "_id": "0817",
    "Number": "792",
    "Name": "Lunala",
    "Element": "Psychic",
    "SecElement": "Ghost",
    "Height": "4.0 m",
    "Weight": "120.0 kh",
    "Species": "Moone Pokémon",
    "Region": "Alola",
    "PkdxEntry": "It is said to be a female evolution of Cosmog. When its third eye activates, away it flies to another world.",
    "ImgUrl": "https://img.pokemondb.net/sprites/home/normal/lunala.png",
    "Form": ""
  },
  {
    "_id": "0818",
    "Number": "793",
    "Name": "Nihilego",
    "Element": "Rock",
    "SecElement": "Poison",
    "Height": "1.2 m",
    "Weight": "55.5 kg",
    "Species": "Parasite Pokémon",
    "Region": "Alola",
    "PkdxEntry": "One of several mysterious Ultra Beasts. People on the street report observing those infested by it suddenly becoming violent.",
    "ImgUrl": "https://img.pokemondb.net/sprites/home/normal/nihilego.png",
    "Form": ""
  },
  {
    "_id": "0819",
    "Number": "794",
    "Name": "Buzzwole",
    "Element": "Bug",
    "SecElement": "Fighting",
    "Height": "2.4 m",
    "Weight": "333.6 kg",
    "Species": "Swollen Pokémon",
    "Region": "Alola",
    "PkdxEntry": "This Ultra Beast appeared from another world. It shows off its body, but whether that display is a boast or a threat remains unclear.",
    "ImgUrl": "https://img.pokemondb.net/sprites/home/normal/buzzwole.png",
    "Form": ""
  },
  {
    "_id": "0820",
    "Number": "795",
    "Name": "Pheromosa",
    "Element": "Bug",
    "SecElement": "Fighting",
    "Height": "1.8 m",
    "Weight": "25.0 kg",
    "Species": "Lissome Pokémon",
    "Region": "Alola",
    "PkdxEntry": "One of the dangerous Ultra Beasts, it has been spotted running across the land at terrific speeds.",
    "ImgUrl": "https://img.pokemondb.net/sprites/home/normal/pheromosa.png",
    "Form": ""
  },
  {
    "_id": "0821",
    "Number": "796",
    "Name": "Xurkitree",
    "Element": "Electric",
    "SecElement": "",
    "Height": "3.8 m",
    "Weight": "100.0 kg",
    "Species": "Glowing Pokémon",
    "Region": "Alola",
    "PkdxEntry": "One of the mysterious life-forms known as Ultra Beasts. Astonishing electric shocks emanate from its entire body, according to witnesses.",
    "ImgUrl": "https://img.pokemondb.net/sprites/home/normal/xurkitree.png",
    "Form": ""
  },
  {
    "_id": "0822",
    "Number": "797",
    "Name": "Celesteela",
    "Element": "Steel",
    "SecElement": "Flying",
    "Height": "9.2 m",
    "Weight": "999.9 kg",
    "Species": "Launch Pokémon",
    "Region": "Alola",
    "PkdxEntry": "It appeared from the Ultra Wormhole. Witnesses observed it flying across the sky at high speed.",
    "ImgUrl": "https://img.pokemondb.net/sprites/home/normal/celesteela.png",
    "Form": ""
  },
  {
    "_id": "0823",
    "Number": "798",
    "Name": "Kartana",
    "Element": "Grass",
    "SecElement": "Steel",
    "Height": "0.3 m",
    "Weight": "0.1 kg",
    "Species": "Drawn Sword Pokémon",
    "Region": "Alola",
    "PkdxEntry": "This Ultra Beast came from the Ultra Wormhole. It seems not to attack enemies on its own, but its sharp body is a dangerous weapon in itself.",
    "ImgUrl": "https://img.pokemondb.net/sprites/home/normal/kartana.png",
    "Form": ""
  },
  {
    "_id": "0824",
    "Number": "799",
    "Name": "Guzzlord",
    "Element": "Dark",
    "SecElement": "Dragon",
    "Height": "5.5 m",
    "Weight": "888.0 kg",
    "Species": "Junkivore Pokémon",
    "Region": "Alola",
    "PkdxEntry": "It has gobbled mountains and swallowed whole buildings, according to reports. It’s one of the Ultra Beasts.",
    "ImgUrl": "https://img.pokemondb.net/sprites/home/normal/guzzlord.png",
    "Form": ""
  },
  {
    "_id": "0825",
    "Number": "800",
    "Name": "Necrozma",
    "Element": "Psychic",
    "SecElement": "",
    "Height": "2.4 m",
    "Weight": "230.0 kg",
    "Species": "Prism Pokémon",
    "Region": "Alola",
    "PkdxEntry": "Reminiscent of the Ultra Beasts, this life-form, apparently asleep underground, is thought to have come from another world in ancient times.",
    "ImgUrl": "https://img.pokemondb.net/sprites/home/normal/necrozma.png",
    "Form": ""
  },
  {
    "_id": "0826",
    "Number": "801",
    "Name": "Magearna",
    "Element": "Steel",
    "SecElement": "Fairy",
    "Height": "1.0 m",
    "Weight": "80.5 kg",
    "Species": "Artificial Pokémon",
    "Region": "Alola",
    "PkdxEntry": "This artificial Pokémon, constructed more than 500 years ago, can understand human speech but cannot itself speak.",
    "ImgUrl": "https://img.pokemondb.net/sprites/home/normal/magearna.png",
    "Form": ""
  },
  {
    "_id": "0827",
    "Number": "802",
    "Name": "Marshadow",
    "Element": "Fighting",
    "SecElement": "Ghost",
    "Height": "0.7 m",
    "Weight": "22.2 kg",
    "Species": "Gloomdweller Pokémon",
    "Region": "Alola",
    "PkdxEntry": "Able to conceal itself in shadows, it never appears before humans, so its very existence was the stuff of myth.",
    "ImgUrl": "https://img.pokemondb.net/sprites/home/normal/marshadow.png",
    "Form": ""
  },
  {
    "_id": "0828",
    "Number": "803",
    "Name": "Poipole",
    "Element": "Poison",
    "SecElement": "",
    "Height": "0.6 m",
    "Weight": "1.8 kg",
    "Species": "Poison Pin Pokémon",
    "Region": "Alola",
    "PkdxEntry": "An Ultra Beast that lives in a different world, it cackles wildly as it sprays its opponents with poison from the needles on its head.",
    "ImgUrl": "https://img.pokemondb.net/sprites/home/normal/poipole.png",
    "Form": ""
  },
  {
    "_id": "0829",
    "Number": "804",
    "Name": "Naganadel",
    "Element": "Poison",
    "SecElement": "Dragon",
    "Height": "3.6 m",
    "Weight": "150.0 kg",
    "Species": "Poison Pin Pokémon",
    "Region": "Alola",
    "PkdxEntry": "One kind of Ultra Beast, it fires a glowing, venomous liquid from its needles. This liquid is also immensely adhesive.",
    "ImgUrl": "https://img.pokemondb.net/sprites/home/normal/naganadel.png",
    "Form": ""
  },
  {
    "_id": "0830",
    "Number": "805",
    "Name": "Stakataka",
    "Element": "Rock",
    "SecElement": "Steel",
    "Height": "5.5 m",
    "Weight": "820.0 kg",
    "Species": "Rampart Pokémon",
    "Region": "Alola",
    "PkdxEntry": "When stone walls started moving and attacking, the brute’s true identity was this mysterious life-form, which brings to mind an Ultra Beast.",
    "ImgUrl": "https://img.pokemondb.net/sprites/home/normal/stakataka.png",
    "Form": ""
  },
  {
    "_id": "0831",
    "Number": "806",
    "Name": "Blacephalon",
    "Element": "Fire",
    "SecElement": "Ghost",
    "Height": "1.8 m",
    "Weight": "13.0 kg",
    "Species": "Fireworks Pokémon",
    "Region": "Alola",
    "PkdxEntry": "It slithers toward people. Then, without warning, it triggers the explosion of its own head. It’s apparently one kind of Ultra Beast.",
    "ImgUrl": "https://img.pokemondb.net/sprites/home/normal/blacephalon.png",
    "Form": ""
  },
  {
    "_id": "0832",
    "Number": "807",
    "Name": "Zeraora",
    "Element": "Electric",
    "SecElement": "",
    "Height": "1.5 m",
    "Weight": "44.5 kg",
    "Species": "Thunderclap Pokémon",
    "Region": "Alola",
    "PkdxEntry": "It electrifies its claws and tears its opponents apart with them. Even if they dodge its attack, they’ll be electrocuted by the flying sparks.",
    "ImgUrl": "https://img.pokemondb.net/sprites/home/normal/zeraora.png",
    "Form": ""
  },
  {
    "_id": "0833",
    "Number": "808",
    "Name": "Meltan",
    "Element": "Steel",
    "SecElement": "",
    "Height": "0.2 m",
    "Weight": "8.0 kg",
    "Species": "Hex Nut Pokémon",
    "Region": "UNKNOWN",
    "PkdxEntry": "It dissolves and eats metal. Circulating liquid metal within its body is how it generates energy.",
    "ImgUrl": "https://img.pokemondb.net/sprites/home/normal/meltan.png",
    "Form": ""
  },
  {
    "_id": "0834",
    "Number": "809",
    "Name": "Melmetal",
    "Element": "Steel",
    "SecElement": "",
    "Height": "2.5 m",
    "Weight": "800.0",
    "Species": "Hex Nut Pokémon",
    "Region": "UNKNOWN",
    "PkdxEntry": "Revered long ago for its capacity to create iron from nothing, for some reason it has come back to life after 3,000 years.",
    "ImgUrl": "https://img.pokemondb.net/sprites/home/normal/melmetal.png",
    "Form": ""
  }
]